signtool/__init__.py
signtool/signtool.py
signtool/signing/__init__.py
signtool/signing/client.py
signtool/util/__init__.py
signtool/util/archives.py
signtool/util/file.py
signtool/util/paths.py
tests/__init__.py
tests/test_signing_client.py
tests/test_signtool.py
tests/test_util_archives.py
tests/test_util_file.py
tests/test_util_paths.py
signtool-4.0.1.dist-info/LICENSE
signtool-4.0.1.dist-info/METADATA
signtool-4.0.1.dist-info/WHEEL
signtool-4.0.1.dist-info/entry_points.txt
signtool-4.0.1.dist-info/top_level.txt
signtool-4.0.1.dist-info/RECORD
